dbis_tm/TM.py
dbis_tm/__init__.py
dbis_tm-2.0.4.dist-info/METADATA
dbis_tm-2.0.4.dist-info/WHEEL
dbis_tm-2.0.4.dist-info/top_level.txt
dbis_tm-2.0.4.dist-info/RECORD
