Metadata-Version: 2.4
Name: dbis-tm
Version: 2.0.4
Summary: RWTH Aachen Computer Science i5/dbis assets for Lecture Datenbanken und Informationssysteme
Author-email: DBIS i5 RWTH Aachen <dbis-vl@dbis.rwth-aachen.de>
Project-URL: Homepage, https://git.rwth-aachen.de/i5/teaching/dbis/dbis-tm
Classifier: Programming Language :: Python :: 3.10
Classifier: Programming Language :: Python :: 3.11
Classifier: Programming Language :: Python :: 3.13
Requires-Python: >=3.10
Requires-Dist: graphviz~=0.20.1
Requires-Dist: dbis-exc-manager~=1.0
Provides-Extra: test
Requires-Dist: black==23.12.1; extra == "test"
Provides-Extra: build
Requires-Dist: twine==6.*; extra == "build"
Requires-Dist: build==1.*; extra == "build"
